_inspect_xls.py
convert_crdb_to_zoho.py
crdb_zoho_converter-0.2.7.dist-info/licenses/LICENSE
crdb_zoho_converter-0.2.7.dist-info/METADATA
crdb_zoho_converter-0.2.7.dist-info/WHEEL
crdb_zoho_converter-0.2.7.dist-info/entry_points.txt
crdb_zoho_converter-0.2.7.dist-info/top_level.txt
crdb_zoho_converter-0.2.7.dist-info/RECORD
