Metadata-Version: 2.4
Name: crdb-zoho-converter
Version: 0.2.7
Summary: Convert CRDB bank statements (XLS/XLSX) into CSV for Zoho Books
Author-email: Leon Kasdorf <lkasdorf@users.noreply.github.com>
License:                                  Apache License
Requires-Python: >=3.10
License-File: LICENSE
Requires-Dist: pandas<3,>=2.2.2
Requires-Dist: xlrd==2.0.1
Requires-Dist: openpyxl>=3.1.0
Dynamic: license-file
